setup.py
paybook/__init__.py
paybook/account.py
paybook/attachment.py
paybook/catalogues.py
paybook/credentials.py
paybook/main.py
paybook/sdk.py
paybook/session.py
paybook/transaction.py
paybook/user.py
paybook.egg-info/PKG-INFO
paybook.egg-info/SOURCES.txt
paybook.egg-info/dependency_links.txt
paybook.egg-info/not-zip-safe
paybook.egg-info/top_level.txt