Metadata-Version: 1.1
Name: paybook
Version: 2.5.6
Summary: Paybook Python Sync SDK
Home-page: https://github.com/Paybook/sync-py.git
Author: Hugo Ochoa
Author-email: hugo@paybook.com
License: MIT
Keywords: Financial Processing Banks Tax
Platform: UNKNOWN
Classifier: Development Status :: 4 - Beta
Classifier: License :: OSI Approved :: MIT License
Classifier: Programming Language :: Python :: 2.7
Classifier: Topic :: Text Processing :: Linguistic
